practical_codes/MonkeyBanana.py
practical_codes/__init__.py
practical_codes/astar.py
practical_codes/bfs.py
practical_codes/dfs.py
practical_codes/nQueens.py
pypract-0.1.0.dist-info/METADATA
pypract-0.1.0.dist-info/WHEEL
pypract-0.1.0.dist-info/top_level.txt
pypract-0.1.0.dist-info/RECORD
