Metadata-Version: 2.1
Name: pypract
Version: 0.1.0
Summary: A collection of practical codes for learning
